ai/__init__.py
ai/codes/1.txt
ai/codes/Agglomerative Clustering KElbow.png
ai/codes/Agglomerative Clustering silhouette.png
ai/codes/Agglomerative Clustering.png
ai/codes/Chapter.10.ipynb
ai/codes/Chapter.2.ipynb
ai/codes/Chapter.3.ipynb
ai/codes/Chapter.4 数据预处理.ipynb
ai/codes/Chapter.5.ipynb
ai/codes/Chapter.6.ipynb
ai/codes/Chapter.7.ipynb
ai/codes/Chapter.8.ipynb
ai/codes/Chapter.9.ipynb
ai/codes/Hugging.py
ai/codes/RBM.png
ai/codes/__init__.py
ai/codes/ai.py
ai/codes/auc-roc.png
ai/codes/b2.txt
ai/codes/bj.py
ai/codes/bread.png
ai/codes/coap-c.py
ai/codes/coap-s.py
ai/codes/data.csv
ai/codes/data.xlsx
ai/codes/dbscan.png
ai/codes/elbow_visualization.jpg
ai/codes/elbow_visualization.png
ai/codes/example.jpg
ai/codes/fs.py
ai/codes/iris_decision_tree
ai/codes/iso.py
ai/codes/iso1.png
ai/codes/jn.cmd
ai/codes/k.py
ai/codes/kmeans1.png
ai/codes/kmeans_clustering.png
ai/codes/logging.conf
ai/codes/logic.png
ai/codes/make_blobs_example.png
ai/codes/make_classification_example.png
ai/codes/make_regression_example.png
ai/codes/model.joblib
ai/codes/model.pkl
ai/codes/oo.py
ai/codes/plot.jpg
ai/codes/plot.png
ai/codes/r.jpg
ai/codes/r.py
ai/codes/regress.png
ai/codes/regression_evaluation_plots.png
ai/codes/result.txt
ai/codes/s.py
ai/codes/sb.py
ai/codes/silhouette_visualization.png
ai/codes/spectral.png
ai/codes/stream_ui_demo.py
ai/codes/streamlit.png
ai/codes/taichi.png
ai/codes/tj.py
ai/codes/.ipynb_checkpoints/Chapter.10-checkpoint.ipynb
ai/codes/.ipynb_checkpoints/Chapter.2-checkpoint.ipynb
ai/codes/.ipynb_checkpoints/Chapter.3-checkpoint.ipynb
ai/codes/.ipynb_checkpoints/Chapter.4 数据预处理-checkpoint.ipynb
ai/codes/.ipynb_checkpoints/Chapter.5-checkpoint.ipynb
ai/codes/.ipynb_checkpoints/Chapter.6-checkpoint.ipynb
ai/codes/.ipynb_checkpoints/Chapter.7-checkpoint.ipynb
ai/codes/.ipynb_checkpoints/Chapter.8-checkpoint.ipynb
ai/codes/.ipynb_checkpoints/Chapter.9-checkpoint.ipynb
ai/codes/.ipynb_checkpoints/Untitled-checkpoint.ipynb
AI_Education_Tools-24.4.28.dist-info/METADATA
AI_Education_Tools-24.4.28.dist-info/WHEEL
AI_Education_Tools-24.4.28.dist-info/entry_points.txt
AI_Education_Tools-24.4.28.dist-info/top_level.txt
AI_Education_Tools-24.4.28.dist-info/RECORD
