Metadata-Version: 2.1
Name: AI_Education_Tools
Version: 24.4.28
Summary: AI Education Tools for Teaching
Home-page: https://github.com/liluqun
Author: Prof.Luqun Li
Author-email: liluqun@gmail.com
Project-URL: Bug Tracker, https://github.com/liluqun
Classifier: Programming Language :: Python :: 3
Classifier: License :: OSI Approved :: MIT License
Classifier: Operating System :: OS Independent
Requires-Python: >=3.5
Requires-Dist: numpy
Requires-Dist: pandas
Requires-Dist: matplotlib
Requires-Dist: pyttsx3
Requires-Dist: openpyxl
Requires-Dist: pydub
Requires-Dist: seaborn
Requires-Dist: xlsxwriter
Requires-Dist: scikit-learn
Requires-Dist: openml
Requires-Dist: scipy
Requires-Dist: importlib-metadata ; python_version > "3.5"
